{
    "Name": "iPhone 7 (China)",
    "Type": "iPhone",
    "image": "iphone_7.png",
    "Info": {
        "Overview": {
            "Introduced": "Sep 2016",
            "Discontinued": "Sep 2019",
            "Model Identifier": "iPhone9,1"
        },
        "Processor": {
            "Processor Name": "Apple A10 Fusion",
            "Processor Speed": "2.3 GHz",
            "Benchmark (SC / MC)": "742 / 1317",
            "Number of Cores": "4 (2 High Performance, 2 High Efficiency)"
        },
        "Software": {
            "Original OS": "iOS 10.0",
            "Maximum OS": "Latest release of iOS 15"
        },
        "Memory": {
            "Built-in Memory": "2 GB LPDDR4"
        },
        "Graphics": {
            "Graphics Chip": "PowerVR GT7600",
            "Graphics Cores": "6"
        },
        "Display": {
            "Display Type": "Retina HD LED-backlit LCD IPS Display",
            "Display Size": "4.7-inch widescreen",
            "Display Resolution": "1334x750"
        },
        "Storage": {
            "Capacity": "32, 128 or 256 GB"
        },
        "Camera": {
            "Rear Camera": "1 - 12 MP",
            "Front Camera": "1 - 7 MP"
        },
        "Battery": {
            "Capacity": "1960 mAh"
        }
    }
}