{
    "Name": "iOS 5",
    "Type": "iOS",
    "image": "ios5.png",
    "Info": {
        "Overview": {
            "Introduced": "Oct 2011",
            "Supported Devices": "<br>iPhone 3GS<br> iPhone 4<br> iPhone 4s<br> iPod touch (3rd generation)<br> iPod touch (4th generation)<br> iPad<br> iPad 2<br> iPad (3rd generation)<br> Apple TV (2nd generation)<br> Apple TV (3rd generation)",
            "Model Identifier": "iOS 5"
        },
        "Versions": {
            "Version": "<table><tbody><tr><td>Version<hr></td><td>Release Date<hr></td></tr><tr><td>5.0</td><td>Oct 12, 2011</td></tr><tr><td>5.0.1</td><td>Nov 10, 2011</td></tr><tr><td>5.1</td><td>Mar 7, 2012</td></tr><tr><td>5.1.1</td><td>May 7, 2012</td></tr></tbody></table>"
        }
    }
}