{
    "Name": "iMac Mid 2006", 
    "Type": "iMac",
    "image": "imac_isight.png",
    "Info": {
          "Overview": {
              "Introduced": "July 2006",
              "Discontinued": "September 2006",
              "Model Identifier": "iMac4,2"
          } ,
          "Processor": {
            "Processor Name": "Intel Core Duo (T2400) ('Yonah')",
            "Processor Speed": "1.83 GHz",
            "Number of Cores": "2"
          },
          "Software": {
            "Original OS": "Mac OS X 10.4.6 (Tiger)",
            "Later OS": "none",
            "Maximum OS": "Mac OS X 10.6.8 (Snow Leopard)"
          },
          "Memory": {
            "Maximum Memory": "2 GB",
            "Supported RAM": "667 MHz DDR2 SO-DIMM"
          },
          "Graphics": {
            "Graphics Chip": "Intel Graphics Media Accelerator (GMA) 950",
            "Graphics Memory": "64 MB DDR2"
          },
          
          "Display": { 
            "Display Type": "17-inch (viewable) TFT LCD",
            "Aspect Ratio": "16:10",
            "Native Resolution": "1440 x 900"
          }

    }
  }